aissemble_model_lineage/__init__.py
aissemble_model_lineage/builder.py
aissemble_model_lineage/facets.py
aissemble_foundation_model_lineage-2.0.0.dist-info/LICENSE
aissemble_foundation_model_lineage-2.0.0.dist-info/LICENSE.txt
aissemble_foundation_model_lineage-2.0.0.dist-info/METADATA
aissemble_foundation_model_lineage-2.0.0.dist-info/WHEEL
aissemble_foundation_model_lineage-2.0.0.dist-info/RECORD
